<?xml version = '1.0' encoding = 'UTF-8'?>
<Flow class="oracle.dbtools.crest.model.design.process.Flow" name="Flow_9" directorySegmentName="seg_0" id="C0A43412-62B2-4284-1625-2D61C5EB6141">
<createdBy>ashik</createdBy>
<createdTime>2025-10-18 15:08:01 UTC</createdTime>
<ownerDesignName>Buying_Car_Insurance</ownerDesignName>
<destination>A948C790-F0F7-57EC-1E8D-73331B8F8071</destination>
<logging>false</logging>
<opCreate>false</opCreate>
<opDelete>false</opDelete>
<opRead>false</opRead>
<opUpdate>false</opUpdate>
<parentObject>B85FB322-E475-396F-8888-19F68D36EBA3</parentObject>
<sourceProcessObject>D5EC024E-9FE9-9CED-99BF-6918AE070FF0</sourceProcessObject>
<targetProcessObject>A948C790-F0F7-57EC-1E8D-73331B8F8071</targetProcessObject>
</Flow>